{
  "meta": {
    "identifier": "TROG0306",
    "pubmed": "27155740",
    "registration": "NCT00110162",
    "publication_date": "2016-05-04 00:00:00",
    "arms": 2,
    "disease": "prostate_cancer",
    "subjects": 293,
    "weibull_by_arm": {
      "delayed_adt": null,
      "immediate_adt": null
    },
    "weibull_max_diff": null,
    "time_scale": "Months",
    "title": "Androgen Deprivation Therapy in Treating Patients With Prostate Cancer",
    "condition_list": [
      "Prostate Cancer"
    ]
  },
  "arms": [
    {
      "events": [
        1,
        1,
        1,
        1,
        1,
        1,
        1,
        1,
        1,
        1,
        1,
        1,
        1,
        1,
        1,
        1,
        1,
        1,
        1,
        1,
        1,
        1,
        1,
        1,
        1,
        1,
        1,
        1,
        1,
        1,
        1,
        0,
        0,
        0,
        0,
        0,
        0,
        0,
        0,
        0,
        0,
        0,
        0,
        0,
        0,
        0,
        0,
        0,
        0,
        0,
        0,
        0,
        0,
        0,
        0,
        0,
        0,
        0,
        0,
        0,
        0,
        0,
        0,
        0,
        0,
        0,
        0,
        0,
        0,
        0,
        0,
        0,
        0,
        0,
        0,
        0,
        0,
        0,
        0,
        0,
        0,
        0,
        0,
        0,
        0,
        0,
        0,
        0,
        0,
        0,
        0,
        0,
        0,
        0,
        0,
        0,
        0,
        0,
        0,
        0,
        0,
        0,
        0,
        0,
        0,
        0,
        0,
        0,
        0,
        0,
        0,
        0,
        0,
        0,
        0,
        0,
        0,
        0,
        0,
        0,
        0,
        0,
        0,
        0,
        0,
        0,
        0,
        0,
        0,
        0,
        0,
        0,
        0,
        0,
        0,
        0,
        0,
        0,
        0,
        0,
        0,
        0,
        0,
        0,
        0,
        0,
        0,
        0,
        0,
        0,
        0
      ],
      "time": [
        12.0,
        14.76,
        19.919999999999998,
        25.68,
        27.48,
        27.96,
        29.759999999999998,
        30.36,
        41.76,
        42.0,
        45.0,
        54.480000000000004,
        58.44,
        59.16,
        59.400000000000006,
        59.760000000000005,
        60.480000000000004,
        62.400000000000006,
        62.519999999999996,
        63.0,
        65.16,
        65.4,
        67.80000000000001,
        72.36,
        74.03999999999999,
        76.92,
        77.64,
        78.6,
        86.16,
        86.28,
        94.80000000000001,
        5.9879999999999995,
        12.54,
        14.04,
        15.0,
        15.66,
        16.32,
        17.700000000000003,
        18.419999999999998,
        19.080000000000002,
        20.34,
        21.18,
        22.14,
        23.1,
        24.900000000000002,
        25.740000000000002,
        26.58,
        27.42,
        28.380000000000003,
        29.22,
        30.06,
        30.900000000000002,
        31.740000000000002,
        32.7,
        33.54,
        34.38,
        35.22,
        37.019999999999996,
        37.68,
        39.0,
        39.54,
        40.38,
        41.22,
        42.06,
        42.839999999999996,
        43.74,
        44.58,
        45.42,
        46.26,
        47.099999999999994,
        48.42,
        48.900000000000006,
        49.38,
        49.739999999999995,
        50.22,
        50.699999999999996,
        51.06,
        51.54,
        52.019999999999996,
        52.5,
        52.86,
        53.34,
        53.94,
        54.17999999999999,
        54.599999999999994,
        55.14,
        55.5,
        55.92,
        56.46,
        56.94,
        57.300000000000004,
        57.78,
        58.260000000000005,
        58.62,
        59.099999999999994,
        59.58,
        60.54,
        61.14,
        61.86,
        62.34,
        62.94,
        63.54,
        64.14,
        64.74,
        65.34,
        65.94,
        66.53999999999999,
        67.14,
        67.74,
        68.34,
        68.94,
        69.53999999999999,
        70.14,
        70.74,
        71.34,
        72.66,
        73.26,
        73.92,
        74.58,
        75.17999999999999,
        75.78,
        76.38,
        77.1,
        77.69999999999999,
        78.30000000000001,
        78.9,
        79.62,
        80.22,
        80.82000000000001,
        81.42,
        82.14,
        82.74,
        83.34,
        85.02,
        85.98,
        86.94,
        88.02,
        88.98,
        89.94,
        91.02,
        91.98,
        92.94,
        94.02,
        94.98,
        96.0,
        96.0,
        96.0,
        96.0,
        96.0,
        96.0,
        96.0
      ],
      "arm_name": "delayed_adt"
    },
    {
      "events": [
        1,
        1,
        1,
        1,
        1,
        1,
        1,
        1,
        1,
        1,
        1,
        1,
        1,
        1,
        1,
        1,
        0,
        0,
        0,
        0,
        0,
        0,
        0,
        0,
        0,
        0,
        0,
        0,
        0,
        0,
        0,
        0,
        0,
        0,
        0,
        0,
        0,
        0,
        0,
        0,
        0,
        0,
        0,
        0,
        0,
        0,
        0,
        0,
        0,
        0,
        0,
        0,
        0,
        0,
        0,
        0,
        0,
        0,
        0,
        0,
        0,
        0,
        0,
        0,
        0,
        0,
        0,
        0,
        0,
        0,
        0,
        0,
        0,
        0,
        0,
        0,
        0,
        0,
        0,
        0,
        0,
        0,
        0,
        0,
        0,
        0,
        0,
        0,
        0,
        0,
        0,
        0,
        0,
        0,
        0,
        0,
        0,
        0,
        0,
        0,
        0,
        0,
        0,
        0,
        0,
        0,
        0,
        0,
        0,
        0,
        0,
        0,
        0,
        0,
        0,
        0,
        0,
        0,
        0,
        0,
        0,
        0,
        0,
        0,
        0,
        0,
        0,
        0,
        0,
        0,
        0,
        0,
        0,
        0,
        0,
        0,
        0,
        0,
        0,
        0,
        0,
        0
      ],
      "time": [
        3.864,
        14.76,
        25.44,
        29.04,
        32.76,
        35.519999999999996,
        37.44,
        51.36,
        54.239999999999995,
        58.32000000000001,
        60.599999999999994,
        63.36,
        68.4,
        71.64,
        77.52,
        79.19999999999999,
        3.114,
        6.1499999999999995,
        8.958,
        13.200000000000001,
        14.399999999999999,
        15.54,
        16.98,
        17.82,
        19.02,
        19.740000000000002,
        21.18,
        22.56,
        23.34,
        25.619999999999997,
        26.28,
        27.72,
        28.68,
        30.0,
        31.44,
        32.099999999999994,
        33.18,
        34.26,
        35.04,
        37.14,
        38.22,
        38.94,
        39.660000000000004,
        40.5,
        41.04,
        42.54,
        42.54,
        43.86,
        44.58,
        45.3,
        46.14,
        46.74,
        48.06,
        49.5,
        49.5,
        50.34,
        50.88,
        51.78,
        51.78,
        53.04,
        53.04,
        53.94,
        54.54,
        55.199999999999996,
        55.739999999999995,
        56.64,
        56.64,
        57.900000000000006,
        57.900000000000006,
        58.739999999999995,
        59.34,
        60.0,
        60.900000000000006,
        61.5,
        62.099999999999994,
        62.099999999999994,
        63.17999999999999,
        63.900000000000006,
        63.900000000000006,
        64.5,
        65.28,
        65.28,
        66.06,
        66.72,
        66.72,
        67.98,
        67.98,
        68.69999999999999,
        69.06,
        69.9,
        69.9,
        70.62,
        71.22,
        71.22,
        72.53999999999999,
        73.08,
        73.08,
        74.46000000000001,
        74.46000000000001,
        74.46000000000001,
        75.84,
        75.84,
        76.38,
        77.16,
        77.16,
        77.82000000000001,
        78.53999999999999,
        78.53999999999999,
        79.26,
        79.80000000000001,
        79.80000000000001,
        81.12,
        81.12,
        81.66,
        82.62,
        82.62,
        82.62,
        83.94,
        83.94,
        85.38,
        85.38,
        86.1,
        86.82000000000001,
        86.82000000000001,
        88.14,
        88.14,
        88.14,
        89.58,
        89.58,
        90.17999999999999,
        91.02,
        91.02,
        91.86,
        92.4,
        92.4,
        93.84,
        93.84,
        94.38,
        95.22,
        95.22,
        96.0,
        96.0
      ],
      "arm_name": "immediate_adt"
    }
  ]
}